finsec/__init__.py
finsec/base.py
finsec/filing.py
finsec/version.py
finsec-0.0.12.dist-info/LICENSE.txt
finsec-0.0.12.dist-info/METADATA
finsec-0.0.12.dist-info/WHEEL
finsec-0.0.12.dist-info/top_level.txt
finsec-0.0.12.dist-info/RECORD
