Metadata-Version: 2.1
Name: finsec
Version: 0.0.12
Summary: Download historical filing data directly from the United States Securities Exchange Commission (SEC)!
Author: Stephen Hogg
Author-email: stephen.hogg.sh@gmail.com
License: Apache
Keywords: pandas,sec,securities exchange commission,finance,pandas datareader
Platform: any
Classifier: License :: OSI Approved :: Apache Software License
Classifier: Development Status :: 4 - Beta
Classifier: Operating System :: OS Independent
Classifier: Intended Audience :: Developers
Classifier: Topic :: Office/Business :: Financial
Classifier: Topic :: Office/Business :: Financial :: Investment
Classifier: Topic :: Scientific/Engineering :: Interface Engine/Protocol Translator
Classifier: Topic :: Software Development :: Libraries
Classifier: Topic :: Software Development :: Libraries :: Python Modules
Classifier: Programming Language :: Python :: 3.10
License-File: LICENSE.txt
Requires-Dist: beautifulsoup4 >=4.11.1
Requires-Dist: pandas >=1.3.5
Requires-Dist: requests >=2.27.1
Requires-Dist: lxml >=4.8.0
Requires-Dist: openpyxl >=3.0.9
